typelike/__init__.py
typelike/version.py
typelike-0.0.0.dist-info/LICENSE.md
typelike-0.0.0.dist-info/METADATA
typelike-0.0.0.dist-info/WHEEL
typelike-0.0.0.dist-info/top_level.txt
typelike-0.0.0.dist-info/zip-safe
typelike-0.0.0.dist-info/RECORD
