Metadata-Version: 2.1
Name: typelike
Version: 0.0.0
Summary: Dummy objects to hold similar types
Home-page: https://www.lockhartlab.org
Author: C. Lockhart
Author-email: chris@lockhartlab.org
License: UNKNOWN
Platform: UNKNOWN
Requires-Dist: numpy
Requires-Dist: pandas
